foundry_client/__init__.py
foundry_client/client.py
foundry_client-2.0.0.dist-info/METADATA
foundry_client-2.0.0.dist-info/WHEEL
foundry_client-2.0.0.dist-info/top_level.txt
foundry_client-2.0.0.dist-info/RECORD
